{
  "generated_at": "2026-03-11T13:23:57.309Z",
  "total_leads": 553,
  "average_score": 37,
  "tiers": {
    "HOT": 0,
    "WARM": 108,
    "COLD": 445
  },
  "industries": {
    "Epoxy": 27,
    "Concrete": 16,
    "SurfacePrep": 2,
    "Automotive": 78,
    "Industrial": 25,
    "Unknown": 405
  },
  "top_leads": [
    {
      "company": "Columbus Epoxy Flooring",
      "city": "Columbus",
      "lead_score": 55,
      "tier": "WARM",
      "industry": "Epoxy"
    },
    {
      "company": "Columbus Garage Floor Coating",
      "city": "Columbus",
      "lead_score": 55,
      "tier": "WARM",
      "industry": "Epoxy"
    },
    {
      "company": "Columbus Epoxy Floors",
      "city": "Columbus",
      "lead_score": 55,
      "tier": "WARM",
      "industry": "Epoxy"
    },
    {
      "company": "Showroom Floors Ltd, Epoxy Floors, Columbus, Oh",
      "city": "Columbus",
      "lead_score": 55,
      "tier": "WARM",
      "industry": "Epoxy"
    },
    {
      "company": "Epoxy Flooring Columbus",
      "city": "Columbus",
      "lead_score": 55,
      "tier": "WARM",
      "industry": "Epoxy"
    },
    {
      "company": "Epoxy and Polished Floors of Columbus",
      "city": "Columbus",
      "lead_score": 55,
      "tier": "WARM",
      "industry": "Epoxy"
    },
    {
      "company": "Ideal Garage Floor Coatings",
      "city": "Columbus",
      "lead_score": 55,
      "tier": "WARM",
      "industry": "Epoxy"
    },
    {
      "company": "Global Epoxy LLC",
      "city": "Columbus",
      "lead_score": 55,
      "tier": "WARM",
      "industry": "Epoxy"
    },
    {
      "company": "Infinite Designs Epoxy Solutions of North Columbus",
      "city": "Columbus",
      "lead_score": 55,
      "tier": "WARM",
      "industry": "Epoxy"
    },
    {
      "company": "Wyckoff Epoxy Flooring",
      "city": "Columbus",
      "lead_score": 55,
      "tier": "WARM",
      "industry": "Epoxy"
    }
  ]
}